[{"_path":"/galleries/gal2","_dir":"galleries","_draft":false,"_partial":false,"_locale":"","title":"Majestic Mountains and Nature's Beauty","description":"","layout":"default","cover":{"src":"/img/galleries/gal2/ankfbvymv9cw3nlhxg6w.webp","alt":"ankfbvymv9cw3nlhxg6w.webp","width":1600,"height":1060},"_type":"markdown","_id":"content:galleries:2.gal2.md","_source":"content","_file":"galleries/2.gal2.md","_stem":"galleries/2.gal2","_extension":"md"},{"_path":"/galleries/gal4","_dir":"galleries","_draft":false,"_partial":false,"_locale":"","title":"Mouthwatering Delights: Savoring the Art of Food Photography","description":"","layout":"default","cover":{"src":"/img/galleries/gal4/ashxosqjkvnf9mhb63oq.webp","alt":"ashxosqjkvnf9mhb63oq.webp","width":1600,"height":1969},"_type":"markdown","_id":"content:galleries:4.gal4.md","_source":"content","_file":"galleries/4.gal4.md","_stem":"galleries/4.gal4","_extension":"md"}]